lahg_ad/Jacobian.py
lahg_ad/__init__.py
lahg_ad/fd.py
lahg_ad/rd.py
lahg_ad-1.2.0.dist-info/LICENSE
lahg_ad-1.2.0.dist-info/METADATA
lahg_ad-1.2.0.dist-info/WHEEL
lahg_ad-1.2.0.dist-info/top_level.txt
lahg_ad-1.2.0.dist-info/RECORD
