Metadata-Version: 2.1
Name: lahg-ad
Version: 1.2.0
Summary: A simple AutoDiff package that supports forward and reverse differentiation, brought to you by the LAHG Society.
Home-page: https://github.com/cs107-lahg/cs107-FinalProject
License: MIT
Platform: UNKNOWN
License-File: LICENSE
Requires-Dist: numpy (~=1.19)
